README.rst
setup.py
cloudmanager/__init__.py
cloudmanager/board.py
cloudmanager/board_orig.py
cloudmanager/configure_device.py
cloudmanager/exceptions.py
cloudmanager/package.py
cloudmanager/server.py
cloudmanager/telnet.py
cloudmanager/utility.py
micropython_cloudmanager.egg-info/PKG-INFO
micropython_cloudmanager.egg-info/SOURCES.txt
micropython_cloudmanager.egg-info/dependency_links.txt
micropython_cloudmanager.egg-info/requires.txt
micropython_cloudmanager.egg-info/top_level.txt
micropython_cloudmanager.egg-info/zip-safe
scripts/mbm
scripts/mbm_sync
scripts/micropython_board_manager