Metadata-Version: 1.0
Name: micropython-cloudmanager
Version: 0.0.142
Summary: Micropython client that allows network attached boards to be controlled from a central redis server
Home-page: https://github.com/dhubbard/micropython-cloudmanager
Author: Dwight Hubbard
Author-email: dwight@dwighthubbard.com
License: MIT
Platform: UNKNOWN
